pipup/__init__.py
pipup/exceptions.py
pipup/freeze.py
pipup/main.py
pipup/req_files.py
pipup-0.3.1.dist-info/AUTHORS.txt
pipup-0.3.1.dist-info/LICENSE.txt
pipup-0.3.1.dist-info/METADATA
pipup-0.3.1.dist-info/WHEEL
pipup-0.3.1.dist-info/entry_points.txt
pipup-0.3.1.dist-info/top_level.txt
pipup-0.3.1.dist-info/RECORD
