Metadata-Version: 2.1
Name: pipup
Version: 0.3.1
Summary: Install or update pip dependency and save it to requirements.txt
Home-page: https://github.com/revsys/pipup
Author: Frank Wiles
Author-email: frank@revsys.com
License: UNKNOWN
Platform: UNKNOWN
Classifier: Development Status :: 4 - Beta
Classifier: Environment :: Console
Classifier: Intended Audience :: Developers
Classifier: License :: OSI Approved :: BSD License
Classifier: Operating System :: OS Independent
Classifier: Programming Language :: Python :: 3
Requires-Dist: click (==7.0)
